golf_companion_533_app/__course_class.py
golf_companion_533_app/__init__.py
golf_companion_533_app/__player_class.py
golf_companion_533_app/player_test.py
golf_companion_533_app/start_game.py
golf_companion_533_app/test_course.py
golf_companion_533_app/__pycache__/__init__.cpython-311.pyc
golf_companion_533_app/__pycache__/player_test.cpython-311.pyc
golf_companion_533_app/__pycache__/test_course.cpython-311.pyc
golf_companion_533_app/course_files/__init__.py
golf_companion_533_app/course_files/okanagan_golf_club_bear.csv
golf_companion_533_app/course_files/shadow_ridge.csv
golf_companion_533_app/course_files/sunset_ranch.csv
golf_companion_533_app/pick_club/__init__.py
golf_companion_533_app/pick_club/pick_test.py
golf_companion_533_app/pick_club/start_picking.py
golf_companion_533_app/pick_club/__pycache__/__init__.cpython-310.pyc
golf_companion_533_app/pick_club/__pycache__/__init__.cpython-311.pyc
golf_companion_533_app/pick_club/__pycache__/__player_class.cpython-311.pyc
golf_companion_533_app/pick_club/__pycache__/pick_test.cpython-310.pyc
golf_companion_533_app/pick_club/__pycache__/pick_test.cpython-311.pyc
golf_companion_533_app/pick_club/__pycache__/start_picking.cpython-310.pyc
golf_companion_533_app/pick_club/__pycache__/start_picking.cpython-311.pyc
golf_companion_533_app/track_score/__init__.py
golf_companion_533_app/track_score/start_tracking.py
golf_companion_533_app/track_score/__pycache__/__course_class.cpython-311.pyc
golf_companion_533_app/track_score/__pycache__/__init__.cpython-310.pyc
golf_companion_533_app/track_score/__pycache__/__init__.cpython-311.pyc
golf_companion_533_app/track_score/__pycache__/start_tracking.cpython-310.pyc
golf_companion_533_app/track_score/__pycache__/start_tracking.cpython-311.pyc
golf_companion_533_app-0.1.3.dist-info/METADATA
golf_companion_533_app-0.1.3.dist-info/WHEEL
golf_companion_533_app-0.1.3.dist-info/top_level.txt
golf_companion_533_app-0.1.3.dist-info/RECORD
