Metadata-Version: 2.1
Name: golf-companion-533-app
Version: 0.1.3
Summary: A golf companion package
Author-email: Dhun Sheth <dhun97@mail.ubc.ca>, Tim Pulfer <tim@gmail.com>
Project-URL: Homepage, https://github.com/Dhunsheth/data_533_group_project
Classifier: Programming Language :: Python :: 3
Classifier: License :: OSI Approved :: MIT License
Classifier: Operating System :: OS Independent
Requires-Python: >=3.9
